Metadata-Version: 2.1
Name: lociP
Version: 0.1
Requires-Dist: numpy==1.22.3
Requires-Dist: tqdm==4.64.0
Requires-Dist: torch==1.12.0
Requires-Dist: scipy==1.7.3
Requires-Dist: scikit-learn==1.1.1
Requires-Dist: pandas==1.4.4
Requires-Dist: openpyxl
Requires-Dist: seaborn==0.12.0
Requires-Dist: matplotlib==3.5.2
